hicrafter/Multi_maps_LH.py
hicrafter/__init__.py
hicrafter/generator.py
hicrafter/tutorial_basic_pipeline.py
hicrafter-0.2.21.dist-info/licenses/LICENSE
hicrafter-0.2.21.dist-info/METADATA
hicrafter-0.2.21.dist-info/WHEEL
hicrafter-0.2.21.dist-info/top_level.txt
hicrafter-0.2.21.dist-info/RECORD
