Metadata-Version: 2.4
Name: hicrafter
Version: 0.2.21
Summary: HI Intensity Mapping generator with LHS sampling & multi-CPU batching
Author: HI Crafter
Author-email: your.email@example.com
License: MIT License
Classifier: Development Status :: 4 - Beta
Classifier: Intended Audience :: Science/Research
Classifier: Topic :: Scientific/Engineering :: Astronomy
Classifier: License :: OSI Approved :: MIT License
Requires-Python: >=3.9
License-File: LICENSE
Requires-Dist: numpy<2.0,>=1.21
Requires-Dist: healpy>=1.15
Requires-Dist: camb>=1.5
Requires-Dist: glass
Requires-Dist: scipy>=1.8
Requires-Dist: cosmology
Requires-Dist: glass-ext-camb>=2023.6
Provides-Extra: dev
Requires-Dist: black; extra == "dev"
Requires-Dist: pytest; extra == "dev"
Requires-Dist: matplotlib; extra == "dev"
Requires-Dist: isort; extra == "dev"
Dynamic: author-email
Dynamic: license-file
Dynamic: requires-python
Dynamic: summary
